PyGamLab/Constants.py
PyGamLab/Converters.py
PyGamLab/Data_Analysis.py
PyGamLab/Functions.py
PyGamLab/__init__.py
PyGamLab/databases/Aflow.py
PyGamLab/databases/COD.py
PyGamLab/databases/Jarvis.py
PyGamLab/databases/Main_DB.py
PyGamLab/databases/Material_projects.py
PyGamLab/databases/__init__.py
PyGamLab/structures/__init__.py
PyGamLab/structures/GAM_architectures/GAM_Graphene.py
PyGamLab/structures/GAM_architectures/GAM_nano_particles.py
PyGamLab/structures/GAM_architectures/GAM_nanotubes.py
PyGamLab/structures/GAM_architectures/GAM_phosphorene.py
PyGamLab/structures/GAM_architectures/GAM_sillicene.py
PyGamLab/structures/GAM_architectures/__init__.py
PyGamLab/structures/Generators/__init__.py
PyGamLab/structures/Generators/auto_bulk.py
PyGamLab/structures/Generators/one_d.py
PyGamLab/structures/Generators/two_d.py
PyGamLab/structures/Generators/zero_d.py
PyGamLab/structures/Primatom/__init__.py
PyGamLab/structures/Primatom/gam_molecule.py
PyGamLab/structures/Primatom/gam_universe.py
PyGamLab/structures/gamvis/__init__.py
PyGamLab/structures/gamvis/gamvis.py
PyGamLab/structures/gamvis/gamvis_engine.py
PyGamLab/structures/io/__init__.py
PyGamLab/structures/io/checker.py
PyGamLab/structures/io/conversions.py
PyGamLab/structures/io/export.py
PyGamLab/structures/io/read.py
pygamlab-1.6.1.dist-info/METADATA
pygamlab-1.6.1.dist-info/WHEEL
pygamlab-1.6.1.dist-info/top_level.txt
pygamlab-1.6.1.dist-info/RECORD
