Metadata-Version: 2.4
Name: PyGamLab
Version: 1.6.1
Summary: A scientific Python library with constants, unit convertors, formulas, and data analysis tools.
Home-page: https://github.com/APMaii/pygamlab/tree/main
Author: Ali Pilehvar Meibody
Author-email: Ali Pilehvar Meibody <alipilehvar1999@Gmail.com>
License-Expression: MIT
Project-URL: Homepage, https://gamlab.aut.ac.ir
Project-URL: Source, https://github.com/APMaii/pygamlab/tree/main
Project-URL: Documentation, https://apmaii.github.io/pygamlab/index.html
Classifier: Programming Language :: Python :: 3
Classifier: Operating System :: OS Independent
Classifier: Intended Audience :: Science/Research
Classifier: Topic :: Scientific/Engineering
Requires-Python: >=3.7
Requires-Dist: numpy
Requires-Dist: pandas
Requires-Dist: scipy
Requires-Dist: matplotlib
Requires-Dist: seaborn
Requires-Dist: scikit-learn
Requires-Dist: ase
Requires-Dist: plotly
Requires-Dist: PyQt5
Requires-Dist: jarvis
Requires-Dist: mp_api
Requires-Dist: aflow
Dynamic: author
Dynamic: home-page
Dynamic: requires-python
